img_resizer/__init__.py
img_resizer/_dir.py
img_resizer/_file.py
img_resizer/_hash_agent.py
img_resizer/_img.py
img_resizer/image_resizer.py
tiny_img/__init__.py
tiny_img/_dir.py
tiny_img/_file.py
tiny_img/_hash_agent.py
tiny_img/_img.py
tiny_img/image_resizer.py
tiny_img-0.1.dist-info/METADATA
tiny_img-0.1.dist-info/WHEEL
tiny_img-0.1.dist-info/top_level.txt
tiny_img-0.1.dist-info/RECORD
